djangorestframework_version_transforms-0.5.0.dist-info/DESCRIPTION.rst
djangorestframework_version_transforms-0.5.0.dist-info/METADATA
djangorestframework_version_transforms-0.5.0.dist-info/metadata.json
djangorestframework_version_transforms-0.5.0.dist-info/RECORD
djangorestframework_version_transforms-0.5.0.dist-info/top_level.txt
djangorestframework_version_transforms-0.5.0.dist-info/WHEEL
rest_framework_transforms/__init__.py
rest_framework_transforms/exceptions.py
rest_framework_transforms/parsers.py
rest_framework_transforms/serializers.py
rest_framework_transforms/transforms.py
rest_framework_transforms/utils.py
rest_framework_transforms/__pycache__/__init__.cpython-34.pyc
rest_framework_transforms/__pycache__/exceptions.cpython-34.pyc
rest_framework_transforms/__pycache__/parsers.cpython-34.pyc
rest_framework_transforms/__pycache__/serializers.cpython-34.pyc
rest_framework_transforms/__pycache__/transforms.cpython-34.pyc
rest_framework_transforms/__pycache__/utils.cpython-34.pyc
