Metadata-Version: 2.0
Name: djangorestframework-version-transforms
Version: 0.5.0
Summary: A library to enable the use of delta transformations for versioning of Django Rest Framwork API representations.
Home-page: https://github.com/mrhwick/django-rest-framework-version-transforms
Author: Matt Hardwick
Author-email: MatthewRHardwick@gmail.com
License: MIT
Platform: UNKNOWN
Classifier: Development Status :: 2 - Pre-Alpha
Classifier: Environment :: Web Environment
Classifier: Framework :: Django
Classifier: Intended Audience :: Developers
Classifier: License :: OSI Approved :: BSD License
Classifier: Operating System :: OS Independent
Classifier: Natural Language :: English
Classifier: Programming Language :: Python :: 2
Classifier: Programming Language :: Python :: 2.7
Classifier: Programming Language :: Python :: 3
Classifier: Programming Language :: Python :: 3.3
Classifier: Programming Language :: Python :: 3.4
Classifier: Topic :: Internet :: WWW/HTTP
